pyethminer/__init__.py
pyethminer/ethminerapi.py
pyethminer/minectl.py
pyethminer-0.4.0.dist-info/LICENSE
pyethminer-0.4.0.dist-info/METADATA
pyethminer-0.4.0.dist-info/WHEEL
pyethminer-0.4.0.dist-info/entry_points.txt
pyethminer-0.4.0.dist-info/top_level.txt
pyethminer-0.4.0.dist-info/RECORD
