Metadata-Version: 2.1
Name: pyethminer
Version: 0.4.0
Summary: Ethminer API client
Home-page: https://github.com/Ventriduct/pyethminer
Author: Ziah Jyothi
Author-email: ventriduct@alphabetical.cc
License: UNKNOWN
Project-URL: Bug Tracker, https://github.com/Ventriduct/pyethminer/issues
Platform: UNKNOWN
Classifier: Programming Language :: Python :: 3
Classifier: License :: OSI Approved :: BSD License
Classifier: Operating System :: OS Independent
Requires-Python: >=3.6
License-File: LICENSE
